vocker/__init__.py
vocker/__main__.py
vocker/cli.py
vocker/dedup.py
vocker/dedup_models.py
vocker/image.py
vocker/integer_to_path.py
vocker/multihash.py
vocker/py.typed
vocker/system.py
vocker/util.py
vocker/util_models.py
vocker/repo/__init__.py
vocker/repo/compression.py
vocker/repo/io.py
vocker-0.2.0.dist-info/METADATA
vocker-0.2.0.dist-info/WHEEL
vocker-0.2.0.dist-info/top_level.txt
vocker-0.2.0.dist-info/RECORD
