Metadata-Version: 2.4
Name: vocker
Version: 0.2.0
Summary: Docker-like manager for virtualenvs
Author-email: Eduard Christian Dumitrescu <eduard.c.dumitrescu@gmail.com>
License: General Public License v3
Project-URL: Homepage, https://hydra.ecd.space/deaduard/vocker/
Project-URL: Changelog, https://hydra.ecd.space/deaduard/vocker/file?name=CHANGELOG.md&ci=trunk
Requires-Dist: atomicwrites
Requires-Dist: attrs
Requires-Dist: boltons
Requires-Dist: cached_property
Requires-Dist: filelock
Requires-Dist: immutabledict
Requires-Dist: marshmallow
Requires-Dist: platformdirs
Requires-Dist: sansio_tools>=1.0.0
Requires-Dist: sqlalchemy_boltons>=2.4.0
Requires-Dist: SQLAlchemy
Requires-Dist: structlog
Requires-Dist: cbor2
Provides-Extra: zstandard
Requires-Dist: pyzstd; extra == "zstandard"
Provides-Extra: tests
Requires-Dist: pytest; extra == "tests"
